genutility/__init__.py
genutility/_file.py
genutility/_files.py
genutility/_func.py
genutility/algorithms.py
genutility/archive.py
genutility/args.py
genutility/aria.py
genutility/asynchronous.py
genutility/atomic.py
genutility/av.py
genutility/bench.py
genutility/binary.py
genutility/browscap.py
genutility/bs4.py
genutility/cache.py
genutility/callbacks.py
genutility/casedict.py
genutility/cholesky.py
genutility/concurrency.py
genutility/config.py
genutility/constants_physics.py
genutility/constants_video.py
genutility/cpython.py
genutility/crypto.py
genutility/csv.py
genutility/cv.py
genutility/datetime.py
genutility/dbm.py
genutility/debug.py
genutility/dict.py
genutility/downloadmanager.py
genutility/encoder.py
genutility/error.py
genutility/exceptions.py
genutility/factorial.py
genutility/file.py
genutility/filesdb.py
genutility/filesystem.py
genutility/fingerprinting.py
genutility/flask.py
genutility/func.py
genutility/gensim.py
genutility/geometry.py
genutility/hash.py
genutility/html.py
genutility/http.py
genutility/huggingface.py
genutility/image.py
genutility/imdb.py
genutility/implementationdetail.py
genutility/indexing.py
genutility/iter.py
genutility/json.py
genutility/latex.py
genutility/lda.py
genutility/logging.py
genutility/markdown.py
genutility/math.py
genutility/mediainfo.py
genutility/memorypath.py
genutility/metrics.py
genutility/metrictree.py
genutility/mongo.py
genutility/msgpack.py
genutility/multihash.py
genutility/net.py
genutility/networkx.py
genutility/nlp.py
genutility/nltk.py
genutility/numba.py
genutility/numpy.py
genutility/object.py
genutility/ops.py
genutility/os.py
genutility/os_mac.py
genutility/os_posix.py
genutility/os_shared.py
genutility/os_win.py
genutility/pandas.py
genutility/parquet.py
genutility/pdf.py
genutility/pickle.py
genutility/pillow.py
genutility/polars.py
genutility/powerpoint.py
genutility/profile.py
genutility/py.typed
genutility/pyhash.py
genutility/rand.py
genutility/rasa.py
genutility/regression.py
genutility-0.0.119.dist-info/LICENSE
genutility-0.0.119.dist-info/METADATA
genutility-0.0.119.dist-info/WHEEL
genutility-0.0.119.dist-info/top_level.txt
genutility-0.0.119.dist-info/RECORD
